__init__.py
VoXera/__init__.py
VoXera/AutomaticSpeechRecognition/__init__.py
VoXera/AutomaticSpeechRecognition/SavedModels/Vosk/large/test/test_simple.py
VoXera/AutomaticSpeechRecognition/SavedModels/Vosk/small/test/test_simple.py
VoXera/AutomaticSpeechRecognition/ScriptsModels/Vosk/VXvosk.py
VoXera/AutomaticSpeechRecognition/ScriptsModels/Vosk/test.py
VoXera/AutomaticSpeechRecognition/ScriptsModels/Whisper/VXwhisper.py
VoXera/AutomaticSpeechRecognition/ScriptsModels/Whisper/test.py
VoXera/KeywordExtraction/PerDeepKE/VXperdeepke.py
VoXera/KeywordExtraction/PerDeepKE/embedding.py
VoXera/KeywordExtraction/PerDeepKE/test.py
VoXera/KeywordExtraction/PerDeepKE/text_segmentation.py
VoXera/Logging/VXlogging.py
VoXera/Logging/__init__.py
VoXera/ParaphraseGeneration/__init__.py
VoXera/ParaphraseGeneration/Evaluate/VXevaluate.py
VoXera/ParaphraseGeneration/Evaluate/__init__.py
VoXera/ParaphraseGeneration/SavedModels/__init__.py
VoXera/ParaphraseGeneration/ScriptsModels/__init__.py
VoXera/ParaphraseGeneration/ScriptsModels/Lab/__init__.py
VoXera/ParaphraseGeneration/ScriptsModels/Lab/Parrot/VXparrot.py
VoXera/ParaphraseGeneration/ScriptsModels/Lab/Parrot/test.py
VoXera/ParaphraseGeneration/ScriptsModels/Lab/Pegasus/VXpegasus.py
VoXera/ParaphraseGeneration/ScriptsModels/Lab/Pegasus/__init__.py
VoXera/ParaphraseGeneration/ScriptsModels/Lab/Pegasus/test.py
VoXera/ParaphraseGeneration/TestData/__init__.py
VoXera-0.0.1.dist-info/LICENSE
VoXera-0.0.1.dist-info/METADATA
VoXera-0.0.1.dist-info/WHEEL
VoXera-0.0.1.dist-info/top_level.txt
VoXera-0.0.1.dist-info/RECORD
