Metadata-Version: 2.1
Name: VoXera
Version: 0.0.1
Summary: An Open-Source Persian Language Techs Toolkit with Python
Author-email: VoXera <boxvoxera@gmail.com>
Project-URL: Home page, https://github.com/VoXera/VoXera
Project-URL: Bug Tracker, https://github.com/VoXera/VoXera/issues
Classifier: Programming Language :: Python :: 3.8
Classifier: Operating System :: OS Independent
Requires-Python: >=3.8
License-File: LICENSE
